static_dicomweb_creator/__init__.py
static_dicomweb_creator/__main__.py
static_dicomweb_creator/creator.py
static_dicomweb_creator/main.py
static_dicomweb_creator/multipart_related.py
static_dicomweb_creator/utils.py
static_dicomweb_creator-0.2.10.dist-info/METADATA
static_dicomweb_creator-0.2.10.dist-info/WHEEL
static_dicomweb_creator-0.2.10.dist-info/entry_points.txt
static_dicomweb_creator-0.2.10.dist-info/licenses/LICENSE
static_dicomweb_creator-0.2.10.dist-info/RECORD
