Metadata-Version: 2.4
Name: static_dicomweb_creator
Version: 0.2.10
Summary: A tool for creating static DICOM web applications
Project-URL: Homepage, https://github.com/akchan/static_dicomweb_creator
Project-URL: Repository, https://github.com/akchan/static_dicomweb_creator
Project-URL: Documentation, https://static-dicomweb-creator.readthedocs.io/
Project-URL: Bug Tracker, https://github.com/akchan/static_dicomweb_creator/issues
Author-email: Satoshi Funayama <akchan.acts@gmail.com>
License-Expression: MIT
License-File: LICENSE
Keywords: dicom,medical imaging,static,web
Classifier: Development Status :: 3 - Alpha
Classifier: Intended Audience :: Healthcare Industry
Classifier: License :: OSI Approved :: MIT License
Classifier: Programming Language :: Python :: 3
Classifier: Programming Language :: Python :: 3.9
Classifier: Programming Language :: Python :: 3.10
Classifier: Programming Language :: Python :: 3.11
Classifier: Programming Language :: Python :: 3.12
Classifier: Topic :: Scientific/Engineering :: Medical Science Apps.
Requires-Python: >=3.9
Requires-Dist: pydicom>=2.0.0
Requires-Dist: pylibjpeg-libjpeg
Requires-Dist: pylibjpeg-rle
Requires-Dist: pylibjpeg>=2.0.1
Provides-Extra: dev
Requires-Dist: flake8; extra == 'dev'
Requires-Dist: isort; extra == 'dev'
Requires-Dist: mypy; extra == 'dev'
Provides-Extra: docs
